{ "人文学院": "103001", "新闻传播学院": "103003", "外文学院": "103004", "经济学院": "103005", "王亚南经济研究院": "103006", "管理学院": "103007", "财务管理与会计研究院": "103008", "法学院": "103009", "知识产权研究院": "103010", "公共事务学院": "103013", "艺术学院": "103015", "海外教育学院/国际学院": "103017", "国际关系学院/南洋研究院": "103018", "数学科学学院": "103019", "物理科学与技术学院": "103020", "化学化工学院": "103021", "材料学院": "103022", "生命科学学院": "103023", "海洋与地球学院": "103024", "环境与生态学院": "103025", "建筑与土木工程学院": "103028", "医学院": "103029", "药学院": "103030", "公共卫生学院": "103031", "能源学院": "103032", "航空航天学院": "103038", "电子科学与技术学院（国家示范性微电子学院）": "103040", "社会与人类学院": "103046", "信息学院": "103048", "创意与创新学院": "103080" }